<?xml version="1.0"?>
<Devices>
	<Device type="custom" id="clockdisplay">
		<Name>Clock Display</Name>
		<ConfigUI>
			<Field type="checkbox" id="useSeconds" defaultValue="false">
				<Label>Use seconds:</Label>
				<Description>Include support for seconds?</Description>
			</Field>
			<Field type="textfield" id="custom1" defaultValue="">
				<Label>Custom format 1:</Label>
				<Description>See https://docs.python.org/2/library/time.html#time.strftime for formats</Description>
			</Field>
			<Field type="textfield" id="custom2" defaultValue="">
				<Label>Custom format 2:</Label>
				<Description>See https://docs.python.org/2/library/time.html#time.strftime for formats</Description>
			</Field>
			<Field type="textfield" id="custom3" defaultValue="">
				<Label>Custom format 3:</Label>
				<Description>See https://docs.python.org/2/library/time.html#time.strftime for formats</Description>
			</Field>
			<Field type="textfield" id="custom4" defaultValue="">
				<Label>Custom format 4:</Label>
				<Description>See https://docs.python.org/2/library/time.html#time.strftime for formats</Description>
			</Field>
			<Field type="textfield" id="custom5" defaultValue="">
				<Label>Custom format 5:</Label>
				<Description>See https://docs.python.org/2/library/time.html#time.strftime for formats</Description>
			</Field>
			<Field type="textfield" id="risesetformat" defaultValue="%H:%M">
				<Label>Format for Sunrise/Sunset:</Label>
				<Description>See https://docs.python.org/2/library/time.html#time.strftime for formats</Description>
			</Field>
			<Field id="durosityMode" type="checkbox">
				<Label>Enable Durosity Mode:</Label>
			</Field>
		</ConfigUI>
		<States>
			<State id="DateUK_DDMMYY"><ValueType>String</ValueType><TriggerLabel>DateUK_DDMMYY</TriggerLabel><ControlPageLabel>DateUK_DDMMYY</ControlPageLabel></State>
			<State id="DateUK_DDMMYYYY"><ValueType>String</ValueType><TriggerLabel>DateUK_DDMMYYYY</TriggerLabel><ControlPageLabel>DateUK_DDMMYYYY</ControlPageLabel></State>
			<State id="DateUS_MMDDYY"><ValueType>String</ValueType><TriggerLabel>DateUS_MMDDYY</TriggerLabel><ControlPageLabel>DateUS_MMDDYY</ControlPageLabel></State>
			<State id="DateUS_MMDDYYYY"><ValueType>String</ValueType><TriggerLabel>DateUS_MMDDYYYY</TriggerLabel><ControlPageLabel>DateUS_MMDDYYYY</ControlPageLabel></State>
			<State id="Day_Long"><ValueType>String</ValueType><TriggerLabel>Day_Long</TriggerLabel><ControlPageLabel>Day_Long</ControlPageLabel></State>
			<State id="Day_Short"><ValueType>String</ValueType><TriggerLabel>Day_Short</TriggerLabel><ControlPageLabel>Day_Short</ControlPageLabel></State>
			<State id="Time_12HMM"><ValueType>String</ValueType><TriggerLabel>Time_12HMM</TriggerLabel><ControlPageLabel>Time_12HMM</ControlPageLabel></State>
			<State id="Time_12HMMSS"><ValueType>String</ValueType><TriggerLabel>Time_12HMMSS</TriggerLabel><ControlPageLabel>Time_12HMMSS</ControlPageLabel></State>
			<State id="Time_24HMM"><ValueType>String</ValueType><TriggerLabel>Time_24HMM</TriggerLabel><ControlPageLabel>Time_24HMM</ControlPageLabel></State>
			<State id="Time_24HMMSS"><ValueType>String</ValueType><TriggerLabel>Time_24HMMSS</TriggerLabel><ControlPageLabel>Time_24HMMSS</ControlPageLabel></State>
			<State id="Time_12HMMAMPM"><ValueType>String</ValueType><TriggerLabel>Time_12HMMAMPM</TriggerLabel><ControlPageLabel>Time_12HMMAMPM</ControlPageLabel></State>
			<State id="Time_12HMMSSAMPM"><ValueType>String</ValueType><TriggerLabel>Time_12HMMSSAMPM</TriggerLabel><ControlPageLabel>Time_12HMMSSAMPM</ControlPageLabel></State>
			<State id="Time_24HMMAMPM"><ValueType>String</ValueType><TriggerLabel>Time_24HMMAMPM</TriggerLabel><ControlPageLabel>Time_24HMMAMPM</ControlPageLabel></State>
			<State id="Time_24HMMSSAMPM"><ValueType>String</ValueType><TriggerLabel>Time_24HMMSSAMPM</TriggerLabel><ControlPageLabel>Time_24HMMSSAMPM</ControlPageLabel></State>
			<State id="Time_12HMMAMPML"><ValueType>String</ValueType><TriggerLabel>Time_12HMMAMPML</TriggerLabel><ControlPageLabel>Time_12HMMAMPML</ControlPageLabel></State>
			<State id="Time_12HMMSSAMPML"><ValueType>String</ValueType><TriggerLabel>Time_12HMMSSAMPML</TriggerLabel><ControlPageLabel>Time_12HMMSSAMPML</ControlPageLabel></State>
			<State id="Time_24HMMAMPML"><ValueType>String</ValueType><TriggerLabel>Time_24HMMAMPML</TriggerLabel><ControlPageLabel>Time_24HMMAMPML</ControlPageLabel></State>
			<State id="Time_24HMMSSAMPML"><ValueType>String</ValueType><TriggerLabel>Time_24HMMSSAMPML</TriggerLabel><ControlPageLabel>Time_24HMMSSAMPML</ControlPageLabel></State>
			<State id="Time_12HHMM"><ValueType>String</ValueType><TriggerLabel>Time_12HHMM</TriggerLabel><ControlPageLabel>Time_12HHMM</ControlPageLabel></State>
			<State id="Time_12HHMMSS"><ValueType>String</ValueType><TriggerLabel>Time_12HHMMSS</TriggerLabel><ControlPageLabel>Time_12HHMMSS</ControlPageLabel></State>
			<State id="Time_24HHMM"><ValueType>String</ValueType><TriggerLabel>Time_24HHMM</TriggerLabel><ControlPageLabel>Time_24HHMM</ControlPageLabel></State>
			<State id="Time_24HHMMSS"><ValueType>String</ValueType><TriggerLabel>Time_24HHMMSS</TriggerLabel><ControlPageLabel>Time_24HHMMSS</ControlPageLabel></State>
			<State id="Time_12HHMMAMPM"><ValueType>String</ValueType><TriggerLabel>Time_12HHMMAMPM</TriggerLabel><ControlPageLabel>Time_12HHMMAMPM</ControlPageLabel></State>
			<State id="Time_12HHMMSSAMPM"><ValueType>String</ValueType><TriggerLabel>Time_12HHMMSSAMPM</TriggerLabel><ControlPageLabel>Time_12HHMMSSAMPM</ControlPageLabel></State>
			<State id="Time_24HHMMAMPM"><ValueType>String</ValueType><TriggerLabel>Time_24HHMMAMPM</TriggerLabel><ControlPageLabel>Time_24HHMMAMPM</ControlPageLabel></State>
			<State id="Time_24HHMMSSAMPM"><ValueType>String</ValueType><TriggerLabel>Time_24HHMMSSAMPM</TriggerLabel><ControlPageLabel>Time_24HHMMSSAMPM</ControlPageLabel></State>
			<State id="Time_12HHMMAMPML"><ValueType>String</ValueType><TriggerLabel>Time_12HHMMAMPML</TriggerLabel><ControlPageLabel>Time_12HHMMAMPML</ControlPageLabel></State>
			<State id="Time_12HHMMSSAMPML"><ValueType>String</ValueType><TriggerLabel>Time_12HHMMSSAMPML</TriggerLabel><ControlPageLabel>Time_12HHMMSSAMPML</ControlPageLabel></State>
			<State id="Time_24HHMMAMPML"><ValueType>String</ValueType><TriggerLabel>Time_24HHMMAMPML</TriggerLabel><ControlPageLabel>Time_24HHMMAMPML</ControlPageLabel></State>
			<State id="Time_24HHMMSSAMPML"><ValueType>String</ValueType><TriggerLabel>Time_24HHMMSSAMPML</TriggerLabel><ControlPageLabel>Time_24HHMMSSAMPML</ControlPageLabel></State>
			<State id="LocalDate"><ValueType>String</ValueType><TriggerLabel>LocalDate</TriggerLabel><ControlPageLabel>LocalDate</ControlPageLabel></State>
			<State id="LocalTime"><ValueType>String</ValueType><TriggerLabel>LocalTime</TriggerLabel><ControlPageLabel>LocalTime</ControlPageLabel></State>
			<State id="Sunrise"><ValueType>String</ValueType><TriggerLabel>Sunrise</TriggerLabel><ControlPageLabel>Sunrise</ControlPageLabel></State>
			<State id="Sunset"><ValueType>String</ValueType><TriggerLabel>Sunset</TriggerLabel><ControlPageLabel>Sunset</ControlPageLabel></State>
			<State id="Custom1"><ValueType>String</ValueType><TriggerLabel>Custom1</TriggerLabel><ControlPageLabel>Custom1</ControlPageLabel></State>
			<State id="Custom2"><ValueType>String</ValueType><TriggerLabel>Custom2</TriggerLabel><ControlPageLabel>Custom2</ControlPageLabel></State>
			<State id="Custom3"><ValueType>String</ValueType><TriggerLabel>Custom3</TriggerLabel><ControlPageLabel>Custom3</ControlPageLabel></State>
			<State id="Custom4"><ValueType>String</ValueType><TriggerLabel>Custom4</TriggerLabel><ControlPageLabel>Custom4</ControlPageLabel></State>
			<State id="Custom5"><ValueType>String</ValueType><TriggerLabel>Custom5</TriggerLabel><ControlPageLabel>Custom5</ControlPageLabel></State>
			<State id="Custom1L"><ValueType>String</ValueType><TriggerLabel>Custom1L</TriggerLabel><ControlPageLabel>Custom1L</ControlPageLabel></State>
			<State id="Custom2L"><ValueType>String</ValueType><TriggerLabel>Custom2L</TriggerLabel><ControlPageLabel>Custom2L</ControlPageLabel></State>
			<State id="Custom3L"><ValueType>String</ValueType><TriggerLabel>Custom3L</TriggerLabel><ControlPageLabel>Custom3L</ControlPageLabel></State>
			<State id="Custom4L"><ValueType>String</ValueType><TriggerLabel>Custom4L</TriggerLabel><ControlPageLabel>Custom4L</ControlPageLabel></State>
			<State id="Custom5L"><ValueType>String</ValueType><TriggerLabel>Custom5L</TriggerLabel><ControlPageLabel>Custom5L</ControlPageLabel></State>
		</States>
		<UiDisplayStateId>LocalTime</UiDisplayStateId>
	</Device>
</Devices>
